libknot/__init__.py
libknot/control.py
libknot/dname.py
libknot/probe.py
libknot-3.3.10.1.dist-info/METADATA
libknot-3.3.10.1.dist-info/WHEEL
libknot-3.3.10.1.dist-info/RECORD
