Metadata-Version: 2.1
Name: libknot
Version: 3.3.10.1
Summary: Python bindings for libknot
Project-URL: Documentation, https://www.knot-dns.cz/documentation
Project-URL: Issues, https://gitlab.nic.cz/knot/knot-dns/-/issues
Project-URL: Source, https://gitlab.nic.cz/knot/knot-dns/-/tree/master/python/libknot
Author-email: "CZ.NIC, z.s.p.o." <knot-dns@labs.nic.cz>
License: GPL-3.0
Classifier: Development Status :: 5 - Production/Stable
Classifier: Intended Audience :: Developers
Classifier: Intended Audience :: System Administrators
Classifier: License :: OSI Approved :: GNU General Public License v3 (GPLv3)
Classifier: Programming Language :: Python :: 3
Classifier: Topic :: Internet :: Name Service (DNS)
Classifier: Topic :: Software Development :: Libraries
Classifier: Topic :: System :: Systems Administration
Requires-Python: >=3.5
